brm.pth
brm.py
brm-0.3.0.dist-info/LICENSE.txt
brm-0.3.0.dist-info/METADATA
brm-0.3.0.dist-info/WHEEL
brm-0.3.0.dist-info/top_level.txt
brm-0.3.0.dist-info/RECORD
